metaflow_extensions/sap/plugins/mfextinit_argowf.py
metaflow_extensions/sap/plugins/argowf/argo_cli.py
metaflow_extensions/sap/plugins/argowf/argo_client.py
metaflow_extensions/sap/plugins/argowf/argo_convert_aggregation.py
metaflow_extensions/sap/plugins/argowf/argo_decorator.py
metaflow_extensions/sap/plugins/argowf/argo_workflow.py
sap_ai_core_metaflow-1.1.22.dist-info/LICENSE.txt
sap_ai_core_metaflow-1.1.22.dist-info/METADATA
sap_ai_core_metaflow-1.1.22.dist-info/WHEEL
sap_ai_core_metaflow-1.1.22.dist-info/top_level.txt
sap_ai_core_metaflow-1.1.22.dist-info/RECORD
