Metadata-Version: 2.1
Name: sap-ai-core-metaflow
Version: 1.1.22
Summary: A Metaflow plugin to execute flows on Argo Workflows
Home-page: https://www.sap.com/
Author: SAP SE
License: SAP DEVELOPER LICENSE AGREEMENT
Project-URL: Documentation, https://blogs.sap.com/2022/04/20/train-your-model-in-sap-ai-core-using-the-metaflow-argo-plugin/
Keywords: SAP AI Core Metaflow Argo Kubernetes
Platform: Linux
Platform: Mac OS-X
Classifier: Development Status :: 7 - Inactive
Classifier: Environment :: Plugins
Classifier: Intended Audience :: Developers
Classifier: Intended Audience :: Other Audience
Classifier: Intended Audience :: Science/Research
Classifier: Natural Language :: English
Classifier: Programming Language :: Python
Classifier: Programming Language :: Python :: 3
Classifier: Programming Language :: Python :: 3.9
Classifier: Programming Language :: Python :: 3.10
Classifier: Programming Language :: Python :: 3.11
Classifier: Programming Language :: Python :: 3.12
Classifier: License :: Other/Proprietary License
Classifier: Operating System :: MacOS :: MacOS X
Classifier: Operating System :: POSIX :: Linux
Classifier: Topic :: Scientific/Engineering :: Artificial Intelligence
Requires-Python: >=3.9
Requires-Dist: metaflow (==2.12.25)
Requires-Dist: kubernetes (==31.0.0)
Provides-Extra: test
Requires-Dist: pytest (>=7.1) ; extra == 'test'
Requires-Dist: pytest-cov[all] ; extra == 'test'
